odoo/addons/hr_holidays_settings/README.rst
odoo/addons/hr_holidays_settings/__init__.py
odoo/addons/hr_holidays_settings/__manifest__.py
odoo/addons/hr_holidays_settings/i18n/ar.po
odoo/addons/hr_holidays_settings/i18n/ca.po
odoo/addons/hr_holidays_settings/i18n/de.po
odoo/addons/hr_holidays_settings/i18n/es.po
odoo/addons/hr_holidays_settings/i18n/fa.po
odoo/addons/hr_holidays_settings/i18n/fi.po
odoo/addons/hr_holidays_settings/i18n/fr.po
odoo/addons/hr_holidays_settings/i18n/hr.po
odoo/addons/hr_holidays_settings/i18n/hr_HR.po
odoo/addons/hr_holidays_settings/i18n/hr_holidays_settings.pot
odoo/addons/hr_holidays_settings/i18n/it.po
odoo/addons/hr_holidays_settings/i18n/nl_NL.po
odoo/addons/hr_holidays_settings/i18n/pt_BR.po
odoo/addons/hr_holidays_settings/i18n/ro.po
odoo/addons/hr_holidays_settings/i18n/sl.po
odoo/addons/hr_holidays_settings/readme/CONTRIBUTORS.rst
odoo/addons/hr_holidays_settings/readme/DESCRIPTION.rst
odoo/addons/hr_holidays_settings/readme/USAGE.rst
odoo/addons/hr_holidays_settings/static/description/icon.png
odoo/addons/hr_holidays_settings/static/description/index.html
odoo/addons/hr_holidays_settings/views/res_config_settings.xml
odoo13_addon_hr_holidays_settings-13.0.1.0.1.dev14.dist-info/METADATA
odoo13_addon_hr_holidays_settings-13.0.1.0.1.dev14.dist-info/WHEEL
odoo13_addon_hr_holidays_settings-13.0.1.0.1.dev14.dist-info/top_level.txt
odoo13_addon_hr_holidays_settings-13.0.1.0.1.dev14.dist-info/RECORD
